data_memory/data_memory.v
module data_memory (
    input clock,
    input mem_write,
    input mem_read,
    input [63:0] address,
    input [63:0] write_data,
    output reg [63:0] read_data
);

  reg [63:0] memory[0:255];

  always @(posedge clock) begin
    if (mem_write) begin
      memory[address[9:2]] <= write_data;
    end
    if (mem_read) begin
      read_data <= memory[address[9:2]];
    end
  end
endmodule

alu/alu.v
module alu (
    input      [63:0] rs1_data,
    input      [63:0] rs2_data,
    input      [ 3:0] alu_ctrl,
    output reg [63:0] result,
    output reg        zero
);

  always @(*) begin
    case (alu_ctrl)
      4'b0000: result = rs1_data + rs2_data;  // ADD
      4'b0001: result = rs1_data - rs2_data;  // SUB
      4'b0010: result = rs1_data & rs2_data;  // AND
      4'b0011: result = rs1_data | rs2_data;  // OR
      4'b0100: result = rs1_data ^ rs2_data;  // XOR
      4'b0101: result = ($signed(rs1_data) < $signed(rs2_data));  // SLT
      4'b0110: result = rs1_data << rs2_data[5:0];  // SLL
      4'b0111: result = rs1_data >> rs2_data[5:0];  // SRL
      4'b1000: result = $signed(rs1_data) >>> rs2_data[5:0];  // SRA
      4'b1001: result = (rs1_data < rs2_data);  // SLTU
      default: result = 64'b0;
    endcase

    zero = (result == 64'b0);
  end
endmodule

alu_control/alu_control.v
module alu_control (
    input      [1:0] alu_op,
    input      [2:0] funct3,
    input      [6:0] funct7,
    output reg [3:0] alu_ctrl
);

  always @(*) begin
    case (alu_op)

      // ADD (loads, stores, jumps)
      2'b00: alu_ctrl = 4'b0000;

      // Branch
      2'b01: begin
        case (funct3)
          3'b000:  alu_ctrl = 4'b0001;  // BEQ
          3'b001:  alu_ctrl = 4'b0001;  // BNE
          3'b100:  alu_ctrl = 4'b0101;  // BLT
          3'b101:  alu_ctrl = 4'b0101;  // BGE
          3'b110:  alu_ctrl = 4'b1001;  // BLTU
          3'b111:  alu_ctrl = 4'b1001;  // BGEU
          default: alu_ctrl = 4'b0000;
        endcase
      end

      // R-type
      2'b10: begin
        case (funct3)
          3'b000:  alu_ctrl = funct7[5] ? 4'b0001 : 4'b0000;
          3'b111:  alu_ctrl = 4'b0010;
          3'b110:  alu_ctrl = 4'b0011;
          3'b100:  alu_ctrl = 4'b0100;
          3'b010:  alu_ctrl = 4'b0101;
          3'b011:  alu_ctrl = 4'b1001;
          3'b001:  alu_ctrl = 4'b0110;
          3'b101:  alu_ctrl = funct7[5] ? 4'b1000 : 4'b0111;
          default: alu_ctrl = 4'b0000;
        endcase
      end

      // I-type
      2'b11: begin
        case (funct3)
          3'b000:  alu_ctrl = 4'b0000;
          3'b111:  alu_ctrl = 4'b0010;
          3'b110:  alu_ctrl = 4'b0011;
          3'b100:  alu_ctrl = 4'b0100;
          3'b010:  alu_ctrl = 4'b0101;
          3'b011:  alu_ctrl = 4'b1001;
          3'b001:  alu_ctrl = 4'b0110;
          3'b101:  alu_ctrl = funct7[5] ? 4'b1000 : 4'b0111;
          default: alu_ctrl = 4'b0000;
        endcase
      end

      default: alu_ctrl = 4'b0000;
    endcase
  end
endmodule

control_unit/control_unit.v
module control_unit (
    input      [6:0] opcode,
    output reg       reg_write,
    output reg       mem_read,
    output reg       mem_write,
    output reg       mem_to_reg,
    output reg       alu_src,     // 0=rs2, 1=imm
    output reg [1:0] pc_src,      // 00=PC+4, 01=branch, 10=JAL/JALR
    output reg [2:0] imm_type,    // I,S,B,U,J
    output reg [1:0] alu_op
);

  localparam [6:0]
    OP_R     = 7'b0110011,
    OP_I     = 7'b0010011,
    OP_LOAD  = 7'b0000011,
    OP_STORE = 7'b0100011,
    OP_BRANCH= 7'b1100011,
    OP_JAL   = 7'b1101111,
    OP_JALR  = 7'b1100111,
    OP_LUI   = 7'b0110111,
    OP_AUIPC = 7'b0010111;

  always @(*) begin
    reg_write  = 0;
    mem_read   = 0;
    mem_write  = 0;
    mem_to_reg = 0;
    alu_src    = 0;
    pc_src     = 2'b00;
    imm_type   = 3'b000;
    alu_op     = 2'b00;

    case (opcode)

      OP_R: begin
        reg_write = 1;
        alu_op    = 2'b10;
      end

      OP_I: begin
        reg_write = 1;
        alu_src   = 1;
        imm_type  = 3'b000;
        alu_op    = 2'b11;
      end

      OP_LOAD: begin
        reg_write  = 1;
        mem_read   = 1;
        mem_to_reg = 1;
        alu_src    = 1;
        imm_type   = 3'b000;
        alu_op     = 2'b00;
      end

      OP_STORE: begin
        mem_write = 1;
        alu_src   = 1;
        imm_type  = 3'b001;
        alu_op    = 2'b00;
      end

      OP_BRANCH: begin
        pc_src   = 2'b01;
        imm_type = 3'b010;
        alu_op   = 2'b01;
      end

      OP_JAL: begin
        reg_write = 1;
        pc_src    = 2'b10;
        imm_type  = 3'b100;
      end

      OP_JALR: begin
        reg_write = 1;
        alu_src   = 1;
        pc_src    = 2'b10;
        imm_type  = 3'b000;
        alu_op    = 2'b00;
      end

      OP_LUI: begin
        reg_write = 1;
        alu_src   = 1;
        imm_type  = 3'b011;
        alu_op    = 2'b00;   // ALU passes imm
      end

      OP_AUIPC: begin
        reg_write = 1;
        alu_src   = 1;
        imm_type  = 3'b011;
        alu_op    = 2'b00;
      end

    endcase
  end
endmodule

immediate_generator/immediate_generator.v
module immediate_generator (
    input  wire [31:0] instruction,
    input  wire [ 2:0] imm_type,
    output reg  [63:0] imm
);

  always @(*) begin
    case (imm_type)
      3'b000: imm = {{52{instruction[31]}}, instruction[31:20]};  // I-type
      3'b001: imm = {{52{instruction[31]}}, instruction[31:25], instruction[11:7]};  // S-type
      3'b010:
      imm = {
        {51{instruction[31]}},
        instruction[31],
        instruction[7],
        instruction[30:25],
        instruction[11:8],
        1'b0
      };  // B-type
      3'b011: imm = {{32{instruction[31]}}, instruction[31:12], 12'b0};  // U-type
      3'b100:
      imm = {
        {43{instruction[31]}},
        instruction[31],
        instruction[19:12],
        instruction[20],
        instruction[30:21],
        1'b0
      };  // J-type
      default: imm = 64'b0;
    endcase
  end

endmodule

register_file/register_file.v
module register_file (
    input  wire        clock,        // Clock signal
    input  wire        reg_write,    // Enables writing to a register
    input  wire [ 4:0] rs1_address,  // Read register 1 address
    input  wire [ 4:0] rs2_address,  // Read register 2 address
    input  wire [ 4:0] rd_address,   // Write register address
    input  wire [63:0] write_data,   // Data to write into rd
    output wire [63:0] rs1_data,     // Output of rs1
    output wire [63:0] rs2_data      // Output of rs2
);

  reg [63:0] registers[0:31];


  assign rs1_data = (rs1_address == 0) ? 64'b0 : registers[rs1_address];
  assign rs2_data = (rs2_address == 0) ? 64'b0 : registers[rs2_address];

  always @(posedge clock) begin
    registers[0] <= 64'b0;
    if (reg_write && rd_address != 0) begin
      registers[rd_address] <= write_data;
    end
  end

endmodule

instruction_memory/instruction_memory.v
module instruction_memory (
    input  [63:0] address,
    output [31:0] instruction
);

  reg [31:0] memory[255];

  initial begin
    $readmemb("instructions.mem", memory);
  end

  assign instruction = memory[address[9:2]];
endmodule

program_counter/program_counter.v
module program_counter (
    input  wire        clock,
    input  wire        reset,
    input  wire [ 1:0] pc_src,
    input  wire        zero,
    input  wire [63:0] imm,
    input  wire [63:0] alu_result,
    output reg  [63:0] pc_current
);

  wire [63:0] pc_plus4;
  wire [63:0] pc_branch;
  wire [63:0] pc_next;
  wire        branch_taken;

  assign pc_plus4 = pc_current + 64'd4;
  assign pc_branch = pc_current + (imm >> 1);
  assign branch_taken = (pc_src == 2'b01) && zero;

  assign pc_next = (pc_src == 2'b01 && branch_taken) ? pc_branch :
                   (pc_src == 2'b10) ? alu_result :
                   pc_plus4;

  always @(posedge clock or posedge reset) begin
    if (reset) pc_current <= 64'b0;
    else pc_current <= pc_next;
  end

endmodule

single_cycle_processor/single_cycle_processor.v
module single_cycle_processor (
    input wire clock,
    input wire reset
);

  wire [63:0] pc;
  wire [63:0] pc_plus4;
  assign pc_plus4 = pc + 64'd4;

  wire [31:0] instruction;
  wire [ 6:0] opcode = instruction[6:0];
  wire [ 2:0] funct3 = instruction[14:12];
  wire [ 6:0] funct7 = instruction[31:25];

  wire [ 4:0] rs1_address = instruction[19:15];
  wire [ 4:0] rs2_address = instruction[24:20];
  wire [ 4:0] rd_address = instruction[11:7];

  wire reg_write, mem_read, mem_write, mem_to_reg;
  wire alu_src;
  wire [1:0] alu_op;
  wire [1:0] pc_src;
  wire [2:0] imm_type;

  wire [63:0] rs1_data, rs2_data;
  wire [63:0] imm;
  wire [63:0] alu_in2;
  wire [63:0] alu_out;
  wire [63:0] mem_data;
  wire [63:0] write_data;
  wire [ 3:0] alu_ctl;
  wire        zero;

  program_counter PC (
      .clock(clock),
      .reset(reset),
      .pc_src(pc_src),
      .zero(zero),
      .imm(imm),
      .alu_result(alu_out),
      .pc_current(pc)
  );

  instruction_memory IM (
      .address(pc),
      .instruction(instruction)
  );

  register_file RF (
      .clock(clock),
      .reg_write(reg_write),
      .rs1_address(rs1_address),
      .rs2_address(rs2_address),
      .rd_address(rd_address),
      .write_data(write_data),
      .rs1_data(rs1_data),
      .rs2_data(rs2_data)
  );

  immediate_generator IG (
      .instruction(instruction),
      .imm_type(imm_type),
      .imm(imm)
  );

  control_unit CU (
      .opcode(opcode),
      .reg_write(reg_write),
      .mem_read(mem_read),
      .mem_write(mem_write),
      .mem_to_reg(mem_to_reg),
      .alu_src(alu_src),
      .alu_op(alu_op),
      .pc_src(pc_src),
      .imm_type(imm_type)
  );

  alu_control AC (
      .alu_op  (alu_op),
      .funct3  (funct3),
      .funct7  (funct7),
      .alu_ctrl(alu_ctl)
  );

  assign alu_in2 = alu_src ? imm : rs2_data;

  alu ALU (
      .rs1_data(rs1_data),
      .rs2_data(alu_in2),
      .alu_ctrl(alu_ctl),
      .result(alu_out),
      .zero(zero)
  );

  data_memory DM (
      .clock(clock),
      .mem_write(mem_write),
      .mem_read(mem_read),
      .address(alu_out),
      .write_data(rs2_data),
      .read_data(mem_data)
  );

  assign write_data = mem_to_reg ? mem_data : (pc_src == 2'b10) ? pc_plus4 : alu_out;

endmodule

single_cycle_processor/single_cycle_processor_test.v
`timescale 1ns / 1ps

module single_cycle_processor_test;

  reg clock;
  reg reset;

  single_cycle_processor cpu (
      .clock(clock),
      .reset(reset)
  );

  initial begin
    clock = 0;
    forever #5 clock = ~clock;
  end

  initial begin
    reset = 1;
    repeat (0.5) @(posedge clock);
    reset = 0;

    forever begin
      @(posedge clock);
      if (cpu.IM.instruction == 32'h00000000) begin
        $display("Halt instruction reached.");
        $finish;
      end
    end
  end

  initial begin
    $dumpfile("single_cycle_processor.vcd");
    $dumpvars(0, single_cycle_processor_test);
  end

endmodule

single_cycle_processor.vcd
$date
	Mon Dec 29 02:34:38 2025
$end
$version
	Icarus Verilog
$end
$timescale
	1ps
$end
$scope module single_cycle_processor_test $end
$var reg 1 ! clock $end
$var reg 1 " reset $end
$scope module cpu $end
$var wire 1 ! clock $end
$var wire 1 " reset $end
$var wire 1 # zero $end
$var wire 64 $ write_data [63:0] $end
$var wire 64 % rs2_data [63:0] $end
$var wire 5 & rs2_address [4:0] $end
$var wire 64 ' rs1_data [63:0] $end
$var wire 5 ( rs1_address [4:0] $end
$var wire 1 ) reg_write $end
$var wire 5 * rd_address [4:0] $end
$var wire 2 + pc_src [1:0] $end
$var wire 64 , pc_plus4 [63:0] $end
$var wire 64 - pc [63:0] $end
$var wire 7 . opcode [6:0] $end
$var wire 1 / mem_write $end
$var wire 1 0 mem_to_reg $end
$var wire 1 1 mem_read $end
$var wire 64 2 mem_data [63:0] $end
$var wire 32 3 instruction [31:0] $end
$var wire 3 4 imm_type [2:0] $end
$var wire 64 5 imm [63:0] $end
$var wire 7 6 funct7 [6:0] $end
$var wire 3 7 funct3 [2:0] $end
$var wire 1 8 alu_src $end
$var wire 64 9 alu_out [63:0] $end
$var wire 2 : alu_op [1:0] $end
$var wire 64 ; alu_in2 [63:0] $end
$var wire 4 < alu_ctl [3:0] $end
$scope module AC $end
$var wire 3 = funct3 [2:0] $end
$var wire 7 > funct7 [6:0] $end
$var wire 2 ? alu_op [1:0] $end
$var reg 4 @ alu_ctrl [3:0] $end
$upscope $end
$scope module ALU $end
$var wire 4 A alu_ctrl [3:0] $end
$var wire 64 B rs2_data [63:0] $end
$var wire 64 C rs1_data [63:0] $end
$var reg 64 D result [63:0] $end
$var reg 1 # zero $end
$upscope $end
$scope module CU $end
$var wire 7 E opcode [6:0] $end
$var parameter 7 F OP_AUIPC $end
$var parameter 7 G OP_BRANCH $end
$var parameter 7 H OP_I $end
$var parameter 7 I OP_JAL $end
$var parameter 7 J OP_JALR $end
$var parameter 7 K OP_LOAD $end
$var parameter 7 L OP_LUI $end
$var parameter 7 M OP_R $end
$var parameter 7 N OP_STORE $end
$var reg 2 O alu_op [1:0] $end
$var reg 1 8 alu_src $end
$var reg 3 P imm_type [2:0] $end
$var reg 1 1 mem_read $end
$var reg 1 0 mem_to_reg $end
$var reg 1 / mem_write $end
$var reg 2 Q pc_src [1:0] $end
$var reg 1 ) reg_write $end
$upscope $end
$scope module DM $end
$var wire 64 R address [63:0] $end
$var wire 1 ! clock $end
$var wire 1 1 mem_read $end
$var wire 1 / mem_write $end
$var wire 64 S write_data [63:0] $end
$var wire 64 T read_data [63:0] $end
$upscope $end
$scope module IG $end
$var wire 3 U imm_type [2:0] $end
$var wire 32 V instruction [31:0] $end
$var reg 64 W imm [63:0] $end
$upscope $end
$scope module IM $end
$var wire 32 X instruction [31:0] $end
$var wire 64 Y address [63:0] $end
$upscope $end
$scope module PC $end
$var wire 64 Z alu_result [63:0] $end
$var wire 1 [ branch_taken $end
$var wire 1 ! clock $end
$var wire 64 \ imm [63:0] $end
$var wire 2 ] pc_src [1:0] $end
$var wire 1 " reset $end
$var wire 1 # zero $end
$var wire 64 ^ pc_plus4 [63:0] $end
$var wire 64 _ pc_next [63:0] $end
$var wire 64 ` pc_branch [63:0] $end
$var reg 64 a pc_current [63:0] $end
$upscope $end
$scope module RF $end
$var wire 1 ! clock $end
$var wire 5 b rd_address [4:0] $end
$var wire 1 ) reg_write $end
$var wire 5 c rs1_address [4:0] $end
$var wire 5 d rs2_address [4:0] $end
$var wire 64 e write_data [63:0] $end
$var wire 64 f rs2_data [63:0] $end
$var wire 64 g rs1_data [63:0] $end
$upscope $end
$upscope $end
$upscope $end
$enddefinitions $end
$comment Show the parameter values. $end
$dumpall
b100011 N
b110011 M
b110111 L
b11 K
b1100111 J
b1101111 I
b10011 H
b1100011 G
b10111 F
$end
#0
$dumpvars
b0 g
bx f
b111 e
b111 d
b0 c
b0 b
b0 a
b111 `
b100 _
b100 ^
b0 ]
b111 \
0[
b111 Z
b0 Y
b11100000000000000010011 X
b111 W
b11100000000000000010011 V
b0 U
b0 T
bx S
b111 R
b0 Q
b0 P
b11 O
b10011 E
b111 D
b0 C
b111 B
b0 A
b0 @
b11 ?
b0 >
b0 =
b0 <
b111 ;
b11 :
b111 9
18
b0 7
b0 6
b111 5
b0 4
b11100000000000000010011 3
b0 2
01
00
0/
b10011 .
b0 -
b100 ,
b0 +
b0 *
1)
b0 (
b0 '
b111 &
bx %
b111 $
0#
1"
0!
$end
#5000
1!
#10000
0!
#15000
1!
#20000
0!
#25000
1!
#30000
0!
#35000
1!
#40000
0!
#45000
1!
#50000
0!
#55000
1!
#60000
0!
#65000
1!
#70000
0!
#75000
1!
#80000
0!
#85000
1!
#90000
0!
#95000
1!
#100000
0!
#105000
1!
#110000
0!
#115000
1!
#120000
0!
#125000
1!
#130000
0!
#135000
1!
#140000
0!
#145000
1!
#150000
0!
#155000
1!
#160000
0!
#165000
1!
#170000
0!
#175000
1!
#180000
0!
#185000
1!
#190000
0!
#195000
0"
1!
#200000
0!
#205000
b11000100 $
b11000100 e
b11000100 9
b11000100 D
b11000100 R
b11000100 Z
b11000100 ;
b11000100 B
b1000 _
b1011 *
b1011 b
b100 &
b100 d
b110 6
b110 >
b11000100 5
b11000100 W
b11000100 \
b1100010000000000010110010011 3
b1100010000000000010110010011 V
b1100010000000000010110010011 X
b1000 ^
b11001000 `
b1000 ,
b100 -
b100 Y
b100 a
1!
#210000
0!
#215000
b100 $
b100 e
b100 9
b100 D
b100 R
b100 Z
b100 ;
b100 B
b1100 _
b11 *
b11 b
b0 6
b0 >
b100 5
b100 W
b100 \
b10000000000000110010011 3
b10000000000000110010011 V
b10000000000000110010011 X
b1100 ^
b1100 `
b1100 ,
b1000 -
b1000 Y
b1000 a
1!
#220000
0!
#225000
b11001000 $
b11001000 e
b11001000 9
b11001000 D
b11001000 R
b11001000 Z
b100 %
b100 S
b100 f
b11000100 '
b11000100 C
b11000100 g
b10 :
b10 ?
b10 O
08
1)
b100 ;
b100 B
b10000 _
b10 *
b10 b
b11 &
b11 d
b1011 (
b1011 c
b110011 .
b110011 E
b11 5
b11 W
b11 \
b1101011000000100110011 3
b1101011000000100110011 V
b1101011000000100110011 X
b10000 ^
b1111 `
b10000 ,
b1100 -
b1100 Y
b1100 a
1!
#230000
0!
#235000
b11000000 $
b11000000 e
b11000100 ;
b11000100 B
0#
b11000000 9
b11000000 D
b11000000 R
b11000000 Z
b11000100 %
b11000100 S
b11000100 f
b11001000 '
b11001000 C
b11001000 g
b10 <
b10 @
b10 A
b10100 _
b11000 *
b11000 b
b1011 &
b1011 d
b10 (
b10 c
b111 7
b111 =
b1011 5
b1011 W
b1011 \
b101100010111110000110011 3
b101100010111110000110011 V
b101100010111110000110011 X
b10100 ^
b11011 `
b10100 ,
b10000 -
b10000 Y
b10000 a
1!
#240000
0!
#245000
b1100 $
b1100 e
b100 ;
b100 B
b1100 9
b1100 D
b1100 R
b1100 Z
b100 %
b100 S
b100 f
b11000000 '
b11000000 C
b11000000 g
b111 <
b111 @
b111 A
b11000 _
b11011 *
b11011 b
b11 &
b11 d
b11000 (
b11000 c
b101 7
b101 =
b11 5
b11 W
b11 \
b1111000101110110110011 3
b1111000101110110110011 V
b1111000101110110110011 X
b11000 ^
b10111 `
b11000 ,
b10100 -
b10100 Y
b10100 a
1!
#250000
0!
#255000
b0 $
b0 e
1#
b1100 ;
b1100 B
b0 9
b0 D
b0 R
b0 Z
b1100 %
b1100 S
b1100 f
b1100 '
b1100 C
b1100 g
b1 <
b1 @
b1 A
b11100 _
b10110 *
b10110 b
b11011 &
b11011 d
b11011 (
b11011 c
b100000 6
b100000 >
b0 7
b0 =
b10000011011 5
b10000011011 W
b10000011011 \
b1000001101111011000101100110011 3
b1000001101111011000101100110011 V
b1000001101111011000101100110011 X
b11100 ^
b10000110011 `
b11100 ,
b11000 -
b11000 Y
b11000 a
1!
#260000
0!
#265000
b0 $
b0 e
1#
b0 9
b0 D
b0 R
b0 Z
b0 ;
b0 B
b0 '
b0 C
b0 g
b0 <
b0 @
b0 A
b1 4
b1 P
b1 U
18
1/
b0 :
b0 ?
b0 O
0)
b100000 _
b0 *
b0 b
b0 (
b0 c
b0 6
b0 >
b11 7
b11 =
b100011 .
b100011 E
b0 5
b0 W
b0 \
b1101100000011000000100011 3
b1101100000011000000100011 V
b1101100000011000000100011 X
b100000 ^
b11100 `
b100000 ,
b11100 -
b11100 Y
b11100 a
1!
#270000
0!
#275000
b1100 $
b1100 e
b1100 2
b1100 T
1#
b0 9
b0 D
b0 R
b0 Z
b0 %
b0 S
b0 f
10
11
1)
b0 4
b0 P
b0 U
18
0/
b0 ;
b0 B
b100100 _
b10011 *
b10011 b
b0 &
b0 d
b11 .
b11 E
b0 5
b0 W
b0 \
b11100110000011 3
b11100110000011 V
b11100110000011 X
b100100 ^
b100000 `
b100100 ,
b100000 -
b100000 Y
b100000 a
1!
#280000
0!
#285000
1[
b0 $
b0 e
b0 2
b0 T
1#
b0 9
b0 D
b0 R
b0 Z
b1100 %
b1100 S
b1100 f
b1100 '
b1100 C
b1100 g
b1 <
b1 @
b1 A
b1 :
b1 ?
b1 O
b10 4
b10 P
b10 U
b1 +
b1 Q
b1 ]
08
00
01
0)
b1100 ;
b1100 B
b110000 _
b1100 *
b1100 b
b11011 &
b11011 d
b10011 (
b10011 c
b0 7
b0 =
b1100011 .
b1100011 E
b1100 5
b1100 W
b1100 \
b1101110011000011001100011 3
b1101110011000011001100011 V
b1101110011000011001100011 X
b101000 ^
b110000 `
b101000 ,
b100100 -
b100100 Y
b100100 a
1!
#290000
0!
#295000
b10001 $
b10001 e
0#
b10001 9
b10001 D
b10001 R
b10001 Z
b10001 ;
b10001 B
b0 <
b0 @
b0 A
0[
bx %
bx S
bx f
b0 '
b0 C
b0 g
18
1)
b11 :
b11 ?
b11 O
b0 4
b0 P
b0 U
b0 +
b0 Q
b0 ]
b1101 *
b1101 b
b10001 &
b10001 d
b0 (
b0 c
b10011 .
b10011 E
b10001 5
b10001 W
b10001 \
b110100 _
b1000100000000011010010011 3
b1000100000000011010010011 V
b1000100000000011010010011 X
b110100 ^
b1000001 `
b110100 ,
b110000 -
b110000 Y
b110000 a
1!
#300000
0!
#305000
b0 $
b0 e
1#
b0 9
b0 D
b0 R
b0 Z
b0 %
b0 S
b0 f
b0 ;
b0 B
b111000 _
b0 *
b0 b
b0 &
b0 d
b0 5
b0 W
b0 \
b10011 3
b10011 V
b10011 X
b111000 ^
b110100 `
b111000 ,
b110100 -
b110100 Y
b110100 a
1!
#310000
0!
#315000
b0 :
b0 ?
b0 O
08
0)
b111100 _
b0 .
b0 E
b0 3
b0 V
b0 X
b111100 ^
b111000 `
b111100 ,
b111000 -
b111000 Y
b111000 a
1!
#320000
0!
#325000
bx $
bx e
bx ;
bx B
x#
bx 9
bx D
bx R
bx Z
bx %
bx S
bx f
bx '
bx C
bx g
b1000000 _
bx *
bx b
bx &
bx d
bx (
bx c
bx 6
bx >
bx 7
bx =
bx .
bx E
bx 5
bx W
bx \
bx 3
bx V
bx X
b1000000 ^
bx `
b1000000 ,
b111100 -
b111100 Y
b111100 a
1!
